dask_deltatable/__init__.py
dask_deltatable/_schema.py
dask_deltatable/core.py
dask_deltatable/py.typed
dask_deltatable/types.py
dask_deltatable/utils.py
dask_deltatable/write.py
dask_deltatable-0.4.0.dist-info/licenses/LICENSE
dask_deltatable-0.4.0.dist-info/METADATA
dask_deltatable-0.4.0.dist-info/WHEEL
dask_deltatable-0.4.0.dist-info/top_level.txt
dask_deltatable-0.4.0.dist-info/RECORD
