Metadata-Version: 2.4
Name: dask-deltatable
Version: 0.4.0
Summary: Dask + Delta Table 
Home-page: https://github.com/dask-contrib/dask-deltatable/
Maintainer: rajagurunath
Maintainer-email: gurunathrajagopal@gmail.com
License: BSD-3-Clause
Classifier: Development Status :: 5 - Production/Stable
Classifier: Intended Audience :: Developers
Classifier: Intended Audience :: Science/Research
Classifier: Topic :: Database
Classifier: Topic :: Scientific/Engineering
Classifier: License :: OSI Approved :: BSD License
Classifier: Programming Language :: Python :: 3
Classifier: Programming Language :: Python :: 3 :: Only
Classifier: Programming Language :: Python :: 3.9
Classifier: Programming Language :: Python :: 3.10
Classifier: Programming Language :: Python :: 3.11
Requires-Python: >=3.9
License-File: LICENSE
Requires-Dist: dask[dataframe]
Requires-Dist: deltalake>=1.1.0
Requires-Dist: fsspec
Requires-Dist: pyarrow
Provides-Extra: dev
Requires-Dist: pytest; extra == "dev"
Requires-Dist: requests; extra == "dev"
Requires-Dist: pytest-cov>=2.10.1; extra == "dev"
Provides-Extra: s3
Requires-Dist: s3fs; extra == "s3"
Requires-Dist: boto3; extra == "s3"
Provides-Extra: uc
Requires-Dist: adlfs; extra == "uc"
Requires-Dist: databricks-sdk; extra == "uc"
Dynamic: classifier
Dynamic: description
Dynamic: description-content-type
Dynamic: home-page
Dynamic: license
Dynamic: license-file
Dynamic: maintainer
Dynamic: maintainer-email
Dynamic: provides-extra
Dynamic: requires-dist
Dynamic: requires-python
Dynamic: summary
